odoo/addons/product_supplierinfo_for_customer_sale/README.rst
odoo/addons/product_supplierinfo_for_customer_sale/__init__.py
odoo/addons/product_supplierinfo_for_customer_sale/__manifest__.py
odoo/addons/product_supplierinfo_for_customer_sale/i18n/ca.po
odoo/addons/product_supplierinfo_for_customer_sale/i18n/de.po
odoo/addons/product_supplierinfo_for_customer_sale/i18n/es.po
odoo/addons/product_supplierinfo_for_customer_sale/i18n/it.po
odoo/addons/product_supplierinfo_for_customer_sale/i18n/product_supplierinfo_for_customer_sale.pot
odoo/addons/product_supplierinfo_for_customer_sale/i18n/pt.po
odoo/addons/product_supplierinfo_for_customer_sale/models/__init__.py
odoo/addons/product_supplierinfo_for_customer_sale/models/sale_order_line.py
odoo/addons/product_supplierinfo_for_customer_sale/readme/CONTRIBUTORS.md
odoo/addons/product_supplierinfo_for_customer_sale/readme/DESCRIPTION.md
odoo/addons/product_supplierinfo_for_customer_sale/readme/ROADMAP.md
odoo/addons/product_supplierinfo_for_customer_sale/readme/USAGE.md
odoo/addons/product_supplierinfo_for_customer_sale/security/ir.model.access.csv
odoo/addons/product_supplierinfo_for_customer_sale/static/description/configuration_customer.png
odoo/addons/product_supplierinfo_for_customer_sale/static/description/description_code.png
odoo/addons/product_supplierinfo_for_customer_sale/static/description/description_code_2.png
odoo/addons/product_supplierinfo_for_customer_sale/static/description/icon.png
odoo/addons/product_supplierinfo_for_customer_sale/static/description/index.html
odoo/addons/product_supplierinfo_for_customer_sale/static/description/search_code.png
odoo/addons/product_supplierinfo_for_customer_sale/static/description/search_code_2.png
odoo/addons/product_supplierinfo_for_customer_sale/tests/__init__.py
odoo/addons/product_supplierinfo_for_customer_sale/tests/test_product_name_search.py
odoo/addons/product_supplierinfo_for_customer_sale/tests/test_product_supplierinfo_for_customer_sale.py
odoo_addon_product_supplierinfo_for_customer_sale-17.0.1.0.0.3.dist-info/METADATA
odoo_addon_product_supplierinfo_for_customer_sale-17.0.1.0.0.3.dist-info/WHEEL
odoo_addon_product_supplierinfo_for_customer_sale-17.0.1.0.0.3.dist-info/top_level.txt
odoo_addon_product_supplierinfo_for_customer_sale-17.0.1.0.0.3.dist-info/RECORD
