Metadata-Version: 2.1
Name: odoo-addon-product_supplierinfo_for_customer_sale
Version: 17.0.1.0.0.3
Requires-Python: >=3.10
Requires-Dist: odoo-addon-product_supplierinfo_for_customer>=17.0dev,<17.1dev
Requires-Dist: odoo>=17.0a,<17.1dev
Summary: Loads in every sale order line the customer code defined in the product
Home-page: https://github.com/OCA/sale-workflow
License: AGPL-3
Author: Agile Business Group,Vauxoo,Odoo Community Association (OCA)
Author-email: support@odoo-community.org
Classifier: Programming Language :: Python
Classifier: Framework :: Odoo
Classifier: Framework :: Odoo :: 17.0
Classifier: License :: OSI Approved :: GNU Affero General Public License v3
